{
  "task_name": "문나이트스킬작업",
  "summary": "대시 스킬 VFX로, 원형 링 형태의 황금빛 이펙트와 폭발적인 중앙 발광 효과가 결합된 구성이다. 링 실루엣 자체는 눈에 띄지만, 캐릭터와 이펙트 간의 경계가 불분명하고 우측 패널형 이펙트 요소가 시각적 혼란을 가중시킨다. 대시 방향성과 타격 시점 전달이 다소 약하며, 다중 전투 환경에서의 식별성이 우려된다.",
  "scores": {
    "hit_timing": 2,
    "readability": 2,
    "silhouette": 3,
    "visual_hierarchy": 2,
    "impact": 3,
    "combat_readability": 2
  },
  "strengths": [
    "황금빛 원형 링 실루엣이 비교적 뚜렷하게 형성되어 스킬의 존재감을 부여함",
    "중앙의 녹색-청색 발광 효과가 에너지 집중감을 표현하는 데 기여함",
    "연기(smoke) 파티클이 지면 접촉감을 어느 정도 보완함"
  ],
  "issues": [
    "대시 방향성이 시각적으로 명확하게 전달되지 않음 — 링과 캐릭터의 이동 벡터가 일치하지 않아 어느 방향으로 이동하는지 파악이 어려움",
    "우측의 반투명 패널형 이펙트 요소가 스킬 의도와 무관하게 읽혀 시각적 노이즈로 작용함",
    "히트 타이밍을 알리는 명확한 플래시 또는 임팩트 프레임이 부재하여 타격 순간 인지가 어려움",
    "캐릭터와 이펙트 레이어가 분리되지 않아 캐릭터 실루엣이 이펙트에 묻히는 현상이 발생함",
    "전체적으로 이펙트 요소들 간의 시각적 우선순위(hierarchy)가 설계되지 않아 시선이 분산됨"
  ],
  "recommended_actions": [
    "대시 방향을 강조하는 모션 블러 또는 트레일 이펙트를 캐릭터 이동 축에 정렬하여 방향성을 명확히 할 것",
    "히트 또는 대시 완료 시점에 짧고 강한 화이트 플래시 프레임(1~2프레임)을 추가하여 타이밍 인지를 강화할 것",
    "우측 패널형 반투명 이펙트의 역할을 재정의하거나 제거하여 핵심 링 이펙트에 시선이 집중되도록 시각 계층을 정리할 것",
    "링 이펙트의 Emissive 강도를 높이고 주변부 파티클의 밝기를 낮춰 핵심 형상과 보조 요소 간의 명도 대비를 확보할 것",
    "다중 전투 상황을 고려하여 이펙트 전체 컬러 팔레트를 단순화하고, 식별 포인트 컬러(예: 황금 링)를 중심으로 통일감을 부여할 것"
  ],
  "overall_score": 2.3,
  "approval_status": "draft"
}